colordet2/ColorDetector.py
colordet2/__init__.py
colordet2-1.0.dist-info/LICENSE.txt
colordet2-1.0.dist-info/METADATA
colordet2-1.0.dist-info/WHEEL
colordet2-1.0.dist-info/top_level.txt
colordet2-1.0.dist-info/RECORD
