Metadata-Version: 2.1
Name: colordet2
Version: 1.0
Summary: Detect colors from image
Home-page: UNKNOWN
Author: Jakub Zalewski
Author-email: jakub.zetka11@gmail.com
License: UNKNOWN
Platform: UNKNOWN
Requires-Dist: numpy
Requires-Dist: opencv-python
